geodatacrawler/__init__.py
geodatacrawler/etl.py
geodatacrawler/mapfile.py
geodatacrawler/metadata.py
geodatacrawler/schemas/iso19139/__init__.py
geodatacrawler/schemas/iso19139/contact.j2
geodatacrawler/schemas/iso19139/main.j2
geodatacrawler/templates/PGM.tpl
geodatacrawler/templates/__init__.py
geodatacrawler/templates/class-line.tpl
geodatacrawler/templates/class-point.tpl
geodatacrawler/templates/class-polygon.tpl
geodatacrawler/templates/class-raster.tpl
geodatacrawler/templates/csv.j2
geodatacrawler/templates/default.map
geodatacrawler/templates/grid.html
geodatacrawler/templates/index.sqlite
geodatacrawler/templates/layer.tpl
geodatacrawler/utils.py
geodatacrawler-1.3.11.dist-info/entry_points.txt
geodatacrawler-1.3.11.dist-info/LICENSE
geodatacrawler-1.3.11.dist-info/WHEEL
geodatacrawler-1.3.11.dist-info/METADATA
geodatacrawler-1.3.11.dist-info/RECORD
