Metadata-Version: 2.1
Name: geodatacrawler
Version: 1.3.11
Summary: a crawler script to extract and author metadata of spatial datasets
Home-page: https://github.com/pvgenuchten/pyGeoDataCrawler
License: MIT
Author: Paul van Genuchten
Author-email: genuchten@yahoo.com
Requires-Python: >=3.8,<4.0
Classifier: License :: OSI Approved :: MIT License
Classifier: Programming Language :: Python :: 3
Classifier: Programming Language :: Python :: 3.10
Classifier: Programming Language :: Python :: 3.8
Classifier: Programming Language :: Python :: 3.9
Requires-Dist: GDAL (>=3.6.2,<4.0.0)
Requires-Dist: Jinja2 (>=3.1.2,<4.0.0)
Requires-Dist: OWSLib (==0.31.0)
Requires-Dist: PyYAML (>=6.0,<7.0)
Requires-Dist: Unidecode (>=1.3.8,<2.0.0)
Requires-Dist: beautifulsoup4 (>=4.12.3,<5.0.0)
Requires-Dist: bibtexparser (>=2.0.0b2,<3.0.0)
Requires-Dist: jinja2-time (>=0.2.0,<0.3.0)
Requires-Dist: mappyfile (>=1.0.0,<2.0.0)
Requires-Dist: openpyxl (>=3.1.2,<4.0.0)
Requires-Dist: pygeometa (==0.16.0)
Requires-Dist: pyproj (>=3.4.0,<4.0.0)
Requires-Dist: pytest (>=7.4.0,<8.0.0)
Requires-Dist: xmltodict (>=0.13.0,<0.14.0)
Project-URL: Repository, https://github.com/pvgenuchten/pyGeoDataCrawler
